protobuf_compiler/__init__.py
protobuf_compiler/__main__.py
protobuf_compiler/args_validation.py
protobuf_compiler/compile_proto.py
protobuf_compiler/input_folder.py
protobuf_compiler/main.py
protobuf_compiler/output_folder.py
protobuf_compiler-1.0.20.data/scripts/protobuf-compiler.py
protobuf_compiler-1.0.20.data/scripts/protopy.py
protobuf_compiler-1.0.20.dist-info/LICENSE
protobuf_compiler-1.0.20.dist-info/METADATA
protobuf_compiler-1.0.20.dist-info/WHEEL
protobuf_compiler-1.0.20.dist-info/entry_points.txt
protobuf_compiler-1.0.20.dist-info/top_level.txt
protobuf_compiler-1.0.20.dist-info/RECORD
