Metadata-Version: 2.1
Name: protobuf_compiler
Version: 1.0.20
Summary: compile all protobuf files and create a single package distribution for can be installed with pip
Home-page: https://github.com/netsaj/python-protobuf-compiler
Author: Fabio Moreno
Author-email: fabiomoreno@outlook.com
License: MIT
Platform: UNKNOWN
Classifier: License :: OSI Approved :: MIT License
Classifier: Programming Language :: Python :: 3
Classifier: Programming Language :: Python :: 3.6
